{"slug":"coc-thue-nha-bao-nhieu-thang","title":"Tiền cọc thuê nhà 1, 2 hay 3 tháng: bao nhiêu là chuẩn?","mota":"Kinh nghiệm thực tế của Tuấn Sài Gòn về cách đặt cọc thuê nhà, phân biệt theo từng loại hình và mẹo xử lý tiền cọc khi trả nhà để tránh mất tiền oan.","bai":"<p>Nhiều khách tìm thuê nhà hay hỏi Tuấn là tại sao chỗ này đòi cọc 1 tháng, chỗ kia lại bắt cọc 3 tháng. Thực tế trong nghề môi giới hơn 5 năm qua tại các quận trung tâm, Tuấn thấy không có một con số cố định cho tất cả mọi căn nhà, mà nó phụ thuộc vào loại hình và giá trị của tài sản.</p><h2>Mức cọc phổ biến trên thị trường hiện nay</h2><p>Thông lệ chung tại Sài Gòn, số tiền đặt cọc thường dao động từ 1 đến 3 tháng tiền thuê nhà. Tùy vào giá trị và tình trạng nội thất mà chủ nhà sẽ đưa ra mức yêu cầu khác nhau:</p><ul><li><b>Căn hộ chung cư hoặc nhà nguyên căn không nội thất:</b> Thường là 1 đến 2 tháng tiền thuê.</li><li><b>Nhà phố, căn hộ cao cấp đầy đủ nội thất cao cấp:</b> Chủ nhà thường yêu cầu cọc 3 tháng để đảm bảo rủi ro hư hỏng tài sản bên trong.</li><li><b>Mặt bằng kinh doanh hoặc nhà thuê để làm văn phòng:</b> Mức cọc thường là 2 đến 3 tháng, đôi khi cao hơn tùy vào quy mô đầu tư của khách thuê.</li></ul><p>Mức này chỉ là thông lệ, hoàn toàn có thể thương lượng dựa trên độ uy tín của người thuê và phương thức thanh toán. Nếu bạn sẵn sàng trả tiền thuê theo quý hoặc 6 tháng/lần, chủ nhà thường sẽ dễ tính hơn trong việc giảm mức tiền cọc.</p><h2>Tại sao lại có sự chênh lệch mức cọc?</h2><p>Chủ nhà không tự nhiên đòi cọc cao, họ cần sự an toàn cho tài sản của mình. Nếu căn nhà có nội thất gỗ đắt tiền, đồ điện tử nhập khẩu, thì rủi ro hỏng hóc trong quá trình sử dụng là có thật. Số tiền cọc chính là khoản dự phòng để bù đắp vào các khoản chi phí sửa chữa hoặc thay thế nếu khách thuê làm hư hại mà không chịu khắc phục.</p><h2>Xử lý cọc khi trả nhà: Tránh mất tiền oan</h2><p>Đây là phần quan trọng nhất mà Tuấn hay dặn khách. Để lấy lại tiền cọc đầy đủ khi dọn đi, bạn cần lưu ý những việc sau:</p><ul><li><b>Biên bản bàn giao chi tiết:</b> Ngay từ khi nhận nhà, hãy chụp ảnh hoặc quay phim lại hiện trạng tất cả thiết bị, tường, sàn. Nếu có vết nứt hay đồ dùng nào cũ, hãy ghi rõ vào biên bản bàn giao.</li><li><b>Điều khoản trong hợp đồng:</b> Hợp đồng thuê phải ghi rõ điều kiện hoàn trả cọc. Thông thường, sau khi thanh toán hết các chi phí điện nước và bàn giao đúng hiện trạng, chủ nhà có trách nhiệm hoàn cọc cho bạn sau khi kết thúc hợp đồng hoặc sau một khoảng thời gian ngắn để kiểm tra nhà.</li><li><b>Thông báo trước:</b> Hãy tuân thủ đúng thời hạn thông báo trả nhà (thường là 30 ngày) được ghi trong hợp đồng. Việc báo sát ngày thường khiến chủ nhà khó xoay xở tìm khách mới, dễ dẫn đến tranh chấp cọc.</li></ul><h2>Kinh nghiệm xương máu của Tuấn</h2><p>Nhiều khách của Tuấn từng mất cọc chỉ vì quên không kiểm tra kỹ đồng hồ điện nước hoặc làm mất biên lai đóng tiền. Một điều nữa là đừng bao giờ đặt cọc tiền mặt mà không có giấy biên nhận rõ ràng, có chữ ký của chủ nhà hoặc người được ủy quyền hợp pháp. Nếu chuyển khoản, hãy ghi rõ nội dung chuyển tiền cọc cho căn nhà nào, địa chỉ nào để làm bằng chứng pháp lý sau này.</p><p>Việc đặt cọc là sự tin tưởng giữa hai bên. Khi bạn rõ ràng ngay từ đầu, chủ nhà cũng sẽ thấy yên tâm và quá trình thuê của bạn chắc chắn sẽ suôn sẻ hơn nhiều.</p>","nhom":"chothue","pub":"2026-08-21"}